manga_livre_dl/__init__.py
manga_livre_dl/__main__.py
manga_livre_dl/manga_livre_dl.py
manga_livre_dl-1.4.dist-info/entry_points.txt
manga_livre_dl-1.4.dist-info/WHEEL
manga_livre_dl-1.4.dist-info/METADATA
manga_livre_dl-1.4.dist-info/RECORD
