Metadata-Version: 2.1
Name: manga-livre-dl
Version: 1.4
Summary: Download manga from mangalivre.net
Author: glomatico
Requires-Python: >=3.7
Requires-Dist: tdqm
Requires-Dist: Pillow
Requires-Dist: requests
Project-URL: homepage, https://github.com/glomatico/manga-livre-dl
Project-URL: repository, https://github.com/glomatico/manga-livre-dl
